{"unique":"0f675d545a72bd1b27b08010a69d72f7","agency_id":"usda","identifier":"USDA-4034","title":"Farmers Markets Search","slug":"farmers-markets-search","description":"AMS works to maintain a current listing of farmers markets throughout the United States. Market information is provided to AMS from various sources including state farmers market associations, state departments of Agriculture and Farmers market managers. The farmers market database is updated annually.","download_url":"","accessURL":null,"distribution":[{"format":"HTML","accessURL":"http://apps.ams.usda.gov/farmersmarkets"}],"adoptions":[{"account":"apievangelist","url":"https://github.com/apievangelist/adopted-federal-agency-dataset/tree/farmers-markets-search"}]}